cs/app/myke/__init__.py
cs/app/myke/__main__.py
cs/app/myke/make.py
cs/app/myke/parse.py
cs.app.myke-20240316.1.dist-info/METADATA
cs.app.myke-20240316.1.dist-info/WHEEL
cs.app.myke-20240316.1.dist-info/entry_points.txt
cs.app.myke-20240316.1.dist-info/top_level.txt
cs.app.myke-20240316.1.dist-info/RECORD
