Metadata-Version: 2.1
Name: cs.app.myke
Version: 20240316.1
Summary: my make program; parallel make tool with superior expression syntax
Author-email: Cameron Simpson <cs@cskk.id.au>
License: GNU General Public License v3 or later (GPLv3+)
Project-URL: URL, https://bitbucket.org/cameron_simpson/css/commits/all
Keywords: python3
Platform: UNKNOWN
Classifier: Programming Language :: Python
Classifier: Programming Language :: Python :: 3
Classifier: Development Status :: 4 - Beta
Classifier: Intended Audience :: Developers
Classifier: Operating System :: OS Independent
Classifier: Topic :: Software Development :: Libraries :: Python Modules
Classifier: License :: OSI Approved :: GNU General Public License v3 or later (GPLv3+)
Requires-Dist: cs.cmdutils >=20240211
Requires-Dist: cs.debug >=20230613.1
Requires-Dist: cs.deco >=20240316
Requires-Dist: cs.excutils >=20230212.1
Requires-Dist: cs.inttypes >=20150120
Requires-Dist: cs.later >=20240305
Requires-Dist: cs.lex >=20240211
Requires-Dist: cs.logutils >=20230212
Requires-Dist: cs.pfx >=20230604
Requires-Dist: cs.py.func >=20230331
Requires-Dist: cs.queues >=20240305
Requires-Dist: cs.result >=20240305
Requires-Dist: cs.threads >=20240303
